azure_eventhubs_client/__init__.py
azure_eventhubs_client/consumer.py
azure_eventhubs_client/producer.py
azure_eventhubs_client/redis_cache.py
azure_eventhubs_client-0.98.1.dist-info/LICENSE
azure_eventhubs_client-0.98.1.dist-info/METADATA
azure_eventhubs_client-0.98.1.dist-info/WHEEL
azure_eventhubs_client-0.98.1.dist-info/top_level.txt
azure_eventhubs_client-0.98.1.dist-info/RECORD
