Metadata-Version: 2.1
Name: azure-eventhubs-client
Version: 0.98.1
Summary: Azure Eventhubs client that simply works
Home-page: https://github.com/KnockriInc/azure_eventhubs_client
Author: Knockri
Author-email: admin@knockri.com
Maintainer: Knockri Inc.
Maintainer-email: admin@knockri.com
License: UNKNOWN
Platform: UNKNOWN
Classifier: Programming Language :: Python :: 3
Classifier: License :: OSI Approved :: MIT License
Classifier: Operating System :: OS Independent
Requires-Dist: redis
Requires-Dist: azure-eventhub (==1.3.3)
